MultiScaleDeformableAttention.cpython-37m-x86_64-linux-gnu.so
functions/__init__.py
functions/ms_deform_attn_func.py
modules/__init__.py
modules/ms_deform_attn.py
MultiScaleDeformableAttention-1.0.dist-info/METADATA
MultiScaleDeformableAttention-1.0.dist-info/WHEEL
MultiScaleDeformableAttention-1.0.dist-info/top_level.txt
MultiScaleDeformableAttention-1.0.dist-info/RECORD
